Metadata-Version: 2.1
Name: lucid3
Version: 1.0.1
Summary: Optical loop finding
Home-page: https://github.com/mxcube/lucid3
Author: ESRF
License: MIT
Project-URL: Source, https://github.com/mxcube/lucid3
Project-URL: Documentation, https://github.com/mxcube/lucid3
Project-URL: Tracker, https://github.com/mxcube/lucid3/issues
Classifier: Intended Audience :: Science/Research
Classifier: License :: OSI Approved :: MIT License
Classifier: Programming Language :: Python :: 3
Requires-Python: >=3.7
Provides-Extra: test
Provides-Extra: dev
License-File: LICENSE
